poet_learning/__init__.py
poet_learning/routes.py
poet_learning-0.1.0.dist-info/WHEEL
poet_learning-0.1.0.dist-info/METADATA
poet_learning-0.1.0.dist-info/RECORD
