Metadata-Version: 2.1
Name: poet-learning
Version: 0.1.0
Summary: 
Author: Anthony
Author-email: anthonyfong100@gmail.com
Requires-Python: >=3.7,<4.0
Classifier: Programming Language :: Python :: 3
Classifier: Programming Language :: Python :: 3.7
Classifier: Programming Language :: Python :: 3.8
Classifier: Programming Language :: Python :: 3.9
Requires-Dist: fastapi (>=0.65.1,<0.66.0)
Requires-Dist: uvicorn (>=0.14.0,<0.15.0)
